MANIFEST.in
README.rst
cached_version.json
setup.cfg
setup.py
nozama/__init__.py
nozama/cloudsearch/__init__.py
nozama/cloudsearch/data/__init__.py
nozama/cloudsearch/data/db.py
nozama/cloudsearch/data/document.py
nozama/cloudsearch/data/tests/__init__.py
nozama/cloudsearch/data/tests/conftest.py
nozama/cloudsearch/data/tests/test_backend_searching.py
nozama/cloudsearch/data/tests/test_documentops.py
nozama_cloudsearch_data.egg-info/PKG-INFO
nozama_cloudsearch_data.egg-info/SOURCES.txt
nozama_cloudsearch_data.egg-info/dependency_links.txt
nozama_cloudsearch_data.egg-info/eager_resources.txt
nozama_cloudsearch_data.egg-info/namespace_packages.txt
nozama_cloudsearch_data.egg-info/not-zip-safe
nozama_cloudsearch_data.egg-info/requires.txt
nozama_cloudsearch_data.egg-info/top_level.txt