Metadata-Version: 1.0
Name: nozama-cloudsearch-data
Version: 1.1.0
Summary: The MongoDB backend storage that nozama-cloudsearch-service relies on. See the http://nozama-cloudsearch.readthedocs.org/en/latest/ for more details. One handy benefit of using Nozama is it provides a way to migrate from Amazon CloudSearch to ElasticSearch.
Home-page: https://github.com/oisinmulvihill/nozama-cloudsearch
Author: Oisin Mulvihill
Author-email: oisin dot mulvihill a-t  gmail dot com
License: BSD
Platform: UNKNOWN
Classifier: Programming Language :: Python
